monad_do/__init__.py
monad_do/applicative.py
monad_do/combinators.py
monad_do/cont.py
monad_do/do_cached.py
monad_do/do_simple.py
monad_do/either.py
monad_do/free.py
monad_do/functor.py
monad_do/io.py
monad_do/list_.py
monad_do/maybe.py
monad_do/monad.py
monad_do/reader.py
monad_do/state.py
monad_do-0.1.1.dist-info/METADATA
monad_do-0.1.1.dist-info/WHEEL
monad_do-0.1.1.dist-info/top_level.txt
monad_do-0.1.1.dist-info/RECORD
