Metadata-Version: 2.1
Name: monad-do
Version: 0.1.1
Summary: Do notation in Python
Home-page: https://github.com/TRCYX/py_monad_do
Author: TRCYX
License: MIT
Keywords: monad
Platform: UNKNOWN
Classifier: Programming Language :: Python :: 3
Classifier: License :: OSI Approved :: MIT License
Classifier: Operating System :: OS Independent
Classifier: Intended Audience :: Developers
Classifier: Intended Audience :: Education
Classifier: Topic :: Education
Classifier: Topic :: Software Development :: Libraries
Requires-Dist: fastcache
